yapyaci/__init__.py
yapyaci/controller.py
yapyaci/exception.py
yapyaci/object_set.py
yapyaci/stream_handler.py
yapyaci/bin/__init__.py
yapyaci/tests/__init__.py
yapyaci-0.6.4.dist-info/METADATA
yapyaci-0.6.4.dist-info/WHEEL
yapyaci-0.6.4.dist-info/top_level.txt
yapyaci-0.6.4.dist-info/RECORD
