Metadata-Version: 2.1
Name: yapyaci
Version: 0.6.4
Summary: Yet Another Python ACI Module
Home-page: https://github.com/ohynderi/YaPiAci
Author: Olivier Hynderick
Author-email: ohynderi@gmail.com
License: MIT
Platform: UNKNOWN
Classifier: License :: OSI Approved :: MIT License
Classifier: Programming Language :: Python :: 3
Classifier: Programming Language :: Python :: 3.7
Requires-Dist: websocket-client
Requires-Dist: python-http-client
